pelican/plugins/series/__init__.py
pelican/plugins/series/conftest.py
pelican/plugins/series/series.py
pelican/plugins/series/test_articles_no_index.py
pelican/plugins/series/test_articles_with_index.py
pelican/plugins/series/test_articles_with_index_over_10.py
pelican/plugins/series/test_data/articles_no_index/series_article_1.md
pelican/plugins/series/test_data/articles_no_index/series_article_2.md
pelican/plugins/series/test_data/articles_no_index/series_article_3.md
pelican/plugins/series/test_data/articles_with_index/series_article_1.md
pelican/plugins/series/test_data/articles_with_index/series_article_2.md
pelican/plugins/series/test_data/articles_with_index/series_article_3.md
pelican/plugins/series/test_data/articles_with_index_over_10/series_article_1.md
pelican/plugins/series/test_data/articles_with_index_over_10/series_article_10.md
pelican/plugins/series/test_data/articles_with_index_over_10/series_article_2.md
pelican/plugins/series/test_data/articles_with_index_over_10/series_article_3.md
pelican_series-3.0.0.dist-info/METADATA
pelican_series-3.0.0.dist-info/WHEEL
pelican_series-3.0.0.dist-info/RECORD
