Metadata-Version: 2.1
Name: pelican-series
Version: 3.0.0
Summary: Series is a Pelican plugin that joins multiple posts into a series
Home-page: https://github.com/pelican-plugins/series
License: AGPL-3.0
Keywords: pelican,plugin,series,multiple
Author: Leonardo Giordani
Author-email: giordani.leonardo@gmail.com
Requires-Python: >=3.8.1,<4.0
Classifier: Development Status :: 5 - Production/Stable
Classifier: Environment :: Console
Classifier: Framework :: Pelican
Classifier: Framework :: Pelican :: Plugins
Classifier: Intended Audience :: End Users/Desktop
Classifier: License :: OSI Approved :: GNU Affero General Public License v3
Classifier: Operating System :: OS Independent
Classifier: Programming Language :: Python :: 3
Classifier: Programming Language :: Python :: 3.9
Classifier: Programming Language :: Python :: 3.10
Classifier: Programming Language :: Python :: 3.11
Classifier: Programming Language :: Python :: 3.12
Classifier: Topic :: Internet :: WWW/HTTP
Classifier: Topic :: Software Development :: Libraries :: Python Modules
Provides-Extra: markdown
Requires-Dist: docutils (!=0.21.post1)
Requires-Dist: markdown (>=3.2) ; extra == "markdown"
Requires-Dist: pelican (>=4.5)
Project-URL: Documentation, https://docs.getpelican.com
Project-URL: Funding, https://donate.getpelican.com/
Project-URL: Issue Tracker, https://github.com/pelican-plugins/series/issues
Project-URL: Repository, https://github.com/pelican-plugins/series
